gdzapi.py
gdzapi-0.1.2.dist-info/METADATA
gdzapi-0.1.2.dist-info/WHEEL
gdzapi-0.1.2.dist-info/RECORD
